{
	"credit": "Made with Blockbench",
	"texture_size": [64, 64],
	"textures": {
		"0": "micro_machinery:blocks/pump",
		"particle": "micro_machinery:blocks/pump"
	},
	"elements": [
		{
			"from": [-2, 3, 1],
			"to": [6, 4, 15],
			"rotation": {"angle": 0, "axis": "y", "origin": [16, 0, 0]},
			"faces": {
				"north": {"uv": [9, 11.75, 11, 12], "texture": "#0"},
				"south": {"uv": [11, 11.75, 9, 12], "texture": "#0"},
				"west": {"uv": [12.5, 15.75, 16, 16], "texture": "#0"}
			}
		},
		{
			"from": [3, 16, 4],
			"to": [4, 17, 12],
			"rotation": {"angle": 0, "axis": "y", "origin": [16, 0, 0]},
			"faces": {
				"west": {"uv": [13.25, 15.75, 15.25, 16], "texture": "#0"}
			}
		}
	]
}